odoo/addons/website_cookie_notice/README.rst
odoo/addons/website_cookie_notice/__init__.py
odoo/addons/website_cookie_notice/__manifest__.py
odoo/addons/website_cookie_notice/controllers/__init__.py
odoo/addons/website_cookie_notice/controllers/main.py
odoo/addons/website_cookie_notice/i18n/bg.po
odoo/addons/website_cookie_notice/i18n/ca.po
odoo/addons/website_cookie_notice/i18n/de.po
odoo/addons/website_cookie_notice/i18n/el_GR.po
odoo/addons/website_cookie_notice/i18n/es.po
odoo/addons/website_cookie_notice/i18n/fr.po
odoo/addons/website_cookie_notice/i18n/gl.po
odoo/addons/website_cookie_notice/i18n/hr.po
odoo/addons/website_cookie_notice/i18n/hr_HR.po
odoo/addons/website_cookie_notice/i18n/it.po
odoo/addons/website_cookie_notice/i18n/nb_NO.po
odoo/addons/website_cookie_notice/i18n/nl.po
odoo/addons/website_cookie_notice/i18n/pt_BR.po
odoo/addons/website_cookie_notice/i18n/pt_PT.po
odoo/addons/website_cookie_notice/i18n/ru.po
odoo/addons/website_cookie_notice/i18n/sl.po
odoo/addons/website_cookie_notice/i18n/website_cookie_notice.pot
odoo/addons/website_cookie_notice/static/description/icon.png
odoo/addons/website_cookie_notice/static/src/js/accept_cookies.js
odoo/addons/website_cookie_notice/templates/website.xml
odoo11_addon_website_cookie_notice-11.0.1.0.1.dist-info/METADATA
odoo11_addon_website_cookie_notice-11.0.1.0.1.dist-info/WHEEL
odoo11_addon_website_cookie_notice-11.0.1.0.1.dist-info/top_level.txt
odoo11_addon_website_cookie_notice-11.0.1.0.1.dist-info/RECORD
